flet_video/__init__.py
flet_video/types.py
flet_video/video.py
flet_video-0.80.5.dist-info/licenses/LICENSE
flutter/flet_video/LICENSE
flutter/flet_video/analysis_options.yaml
flutter/flet_video/pubspec.lock
flutter/flet_video/pubspec.yaml
flutter/flet_video/lib/flet_video.dart
flutter/flet_video/lib/src/extension.dart
flutter/flet_video/lib/src/video.dart
flutter/flet_video/lib/src/utils/file_utils_io.dart
flutter/flet_video/lib/src/utils/file_utils_web.dart
flutter/flet_video/lib/src/utils/video.dart
flet_video-0.80.5.dist-info/METADATA
flet_video-0.80.5.dist-info/WHEEL
flet_video-0.80.5.dist-info/top_level.txt
flet_video-0.80.5.dist-info/RECORD
